fake_detector/__init__.py
fake_detector/api.py
fake_detector/detector.py
fake_detector-0.1.1.dist-info/METADATA
fake_detector-0.1.1.dist-info/WHEEL
fake_detector-0.1.1.dist-info/entry_points.txt
fake_detector-0.1.1.dist-info/top_level.txt
fake_detector-0.1.1.dist-info/RECORD
